{
  "version": "0.1.0",
  "kind": "phrases",
  "phrases": [
    {
      "kind": "afact",
      "name": "controller",
      "type": "String"
    },
    {
      "kind": "afact",
      "name": "processor",
      "type": "String"
    },
    {
      "kind": "afact",
      "name": "third-country",
      "type": "String"
    },
    {
      "kind": "afact",
      "name": "court-judgment",
      "type": "String"
    },
    {
      "kind": "afact",
      "name": "administrative-decision",
      "type": "String"
    },
    {
      "kind": "afact",
      "name": "international-agreement",
      "type": "String"
    },
    {
      "kind": "cfact",
      "name": "requires-transfer",
      "identified-by": [
        "courts-judgment",
        "third-country",
        "data"
      ]
    },
    {
      "kind": "cfact",
      "name": "requires-disclosure",
      "identified-by": [
        "administrative-decision",
        "third-country",
        "data"
      ]
    },
    {
      "kind": "cfact",
      "name": "based-on-international-agreement",
      "identified-by": [
        "international-agreement",
        "third-country"
      ]
    },
    {
      "kind": "act",
      "name": "recognize-enforce-transfer",
      "actor": "controller",
      "related-to": [
        "data"
      ],
      "holds-when": [
        {
          "operator": "AND",
          "operands": [
            {
              "identifier": "requires-transfer",
              "operands": []
            },
            {
              "identifier": "based-on-international-agreement",
              "operands": []
            }
          ]
        }
      ],
      "creates": [
        {
          "identifier": "transfer-duty",
          "operands": []
        }
      ]
    },
    {
      "kind": "act",
      "name": "recognize-enforce-disclosure",
      "actor": "processor",
      "related-to": [
        "data"
      ],
      "holds-when": [
        {
          "operator": "AND",
          "operands": [
            {
              "identifier": "requires-disclosure",
              "operands": []
            },
            {
              "identifier": "based-on-international-agreement",
              "operands": []
            }
          ]
        }
      ],
      "creates": [
        {
          "identifier": "disclosure-duty",
          "operands": []
        }
      ]
    },
    {
      "kind": "duty",
      "name": "transfer-duty",
      "holder": "controller",
      "claimant": "third-country",
      "related-to": [
        "data"
      ]
    },
    {
      "kind": "duty",
      "name": "disclosure-duty",
      "holder": "processor",
      "claimant": "third-country",
      "related-to": [
        "data"
      ]
    }
  ],
  "updates": true
}