{
  "version": "0.1.0",
  "kind": "phrases",
  "phrases": [
    {
      "kind": "afact",
      "name": "controller",
      "type": "String"
    },
    {
      "kind": "afact",
      "name": "processor",
      "type": "String"
    },
    {
      "kind": "afact",
      "name": "third-country",
      "type": "String"
    },
    {
      "kind": "afact",
      "name": "personal-data",
      "type": "String"
    },
    {
      "kind": "afact",
      "name": "international-agreement",
      "type": "String"
    },
    {
      "kind": "cfact",
      "name": "legal-decision",
      "identified-by": [
        "third-country",
        "controller",
        "processor"
      ]
    },
    {
      "kind": "cfact",
      "name": "agreement-in-force",
      "identified-by": [
        "third-country",
        "international-agreement"
      ]
    },
    {
      "kind": "act",
      "name": "authorize-transfer",
      "actor": "controller",
      "related-to": [
        "personal-data"
      ],
      "holds-when": [
        {
          "operator": "AND",
          "operands": [
            {
              "identifier": "legal-decision",
              "operands": []
            },
            {
              "identifier": "agreement-in-force",
              "operands": []
            }
          ]
        }
      ],
      "creates": [
        {
          "identifier": "transfer-authorization",
          "operands": []
        }
      ]
    },
    {
      "kind": "duty",
      "name": "transfer-authorization",
      "holder": "controller",
      "claimant": "third-country",
      "related-to": [
        "personal-data"
      ]
    }
  ],
  "updates": true
}